{
  "_documentation": "Best VIBMask hyperparameters for SYN2 (paper \u00a75.1). Reproduces: TPR=100.00%, FDR=0.00%, CFSR=0.00%, test_acc=0.9028. Selected via Optuna TPE over 130-180 trials.",
  "dataset": "syn2",
  "data_alpha": 2.0,
  "n_train": 5000,
  "n_test": 5000,
  "n_seeds": 5,
  "train_config": {
    "batch_size": 128,
    "val_fraction": 0.1,
    "learning_rate": 0.0027338888901156165,
    "weight_decay": 0.0001,
    "max_iters": 20000,
    "early_stop_patience": 1000,
    "num_selectors": 5,
    "sigma": 0.9525484443167229,
    "train_sigma": false,
    "sel_hidden": [
      128,
      128,
      128,
      128,
      128
    ],
    "pred_hidden": [
      128
    ],
    "layer_norm": true,
    "activation": "relu",
    "pred_dropout": 0.0,
    "beta": 0.0,
    "gamma": 1e-05,
    "warmup_iters": 5000,
    "gate_type": "hard_concrete",
    "hc_beta": 0.34395240003846916,
    "ema_decay": 0.99,
    "lr_schedule": "constant",
    "label_smoothing": 0.0,
    "grad_clip": 1.0,
    "bootstrap": true,
    "classification": true,
    "log_every": 500,
    "device": "cpu"
  },
  "soft_inference": true
}